{
  "multipart": [
    {
      "apply": {
        "model": "electric-gear:block/copper_pipeline"
      },
      "when": {
        "facing": "up",
        "up": "true"
      }
    },
    {
      "apply": {
        "model": "electric-gear:block/copper_pipeline_flat"
      },
      "when": {
        "facing": "up",
        "up": "false"
      }
    },
    {
      "apply": {
        "model": "electric-gear:block/copper_pipeline",
        "x": 180
      },
      "when": {
        "facing": "down",
        "up": "true"
      }
    },
    {
      "apply": {
        "model": "electric-gear:block/copper_pipeline_flat",
        "x": 180
      },
      "when": {
        "facing": "down",
        "up": "false"
      }
    },
    {
      "apply": {
        "model": "electric-gear:block/copper_pipeline",
        "x": 90
      },
      "when": {
        "facing": "north",
        "up": "true"
      }
    },
    {
      "apply": {
        "model": "electric-gear:block/copper_pipeline_flat",
        "x": 90
      },
      "when": {
        "facing": "north",
        "up": "false"
      }
    },
    {
      "apply": {
        "model": "electric-gear:block/copper_pipeline",
        "x": 90,
        "y": 180
      },
      "when": {
        "facing": "south",
        "up": "true"
      }
    },
    {
      "apply": {
        "model": "electric-gear:block/copper_pipeline_flat",
        "x": 90,
        "y": 180
      },
      "when": {
        "facing": "south",
        "up": "false"
      }
    },
    {
      "apply": {
        "model": "electric-gear:block/copper_pipeline",
        "x": 90,
        "y": 270
      },
      "when": {
        "facing": "west",
        "up": "true"
      }
    },
    {
      "apply": {
        "model": "electric-gear:block/copper_pipeline_flat",
        "x": 90,
        "y": 270
      },
      "when": {
        "facing": "west",
        "up": "false"
      }
    },
    {
      "apply": {
        "model": "electric-gear:block/copper_pipeline",
        "x": 90,
        "y": 90
      },
      "when": {
        "facing": "east",
        "up": "true"
      }
    },
    {
      "apply": {
        "model": "electric-gear:block/copper_pipeline_flat",
        "x": 90,
        "y": 90
      },
      "when": {
        "facing": "east",
        "up": "false"
      }
    }
  ]
}